israel_rail_api-0.1.4.dist-info/licenses/LICENSE
israelrailapi/__init__.py
israelrailapi/api.py
israelrailapi/schedule.py
israelrailapi/stations.py
israelrailapi/train_station.py
israel_rail_api-0.1.4.dist-info/METADATA
israel_rail_api-0.1.4.dist-info/WHEEL
israel_rail_api-0.1.4.dist-info/top_level.txt
israel_rail_api-0.1.4.dist-info/RECORD
