Metadata-Version: 2.4
Name: israel-rail-api
Version: 0.1.4
Summary: Israeli Rail unofficial API
Home-page: https://github.com/sh0oki/israel-rail-api
Author: sh0oki
License: MIT
License-File: LICENSE
Requires-Dist: requests
Requires-Dist: pytz
Dynamic: author
Dynamic: description
Dynamic: description-content-type
Dynamic: home-page
Dynamic: license
Dynamic: license-file
Dynamic: requires-dist
Dynamic: summary
